{"otherData": {},"traceEvents":[{"cat":"function","dur":29513,"name":"bool  MemoryPool::Init(void)","ph":"X","pid":0,"tid":3951767690,"ts":1289551520200},{"cat":"function","dur":4,"name":"bool  ResourceCatalog::Init(void)","ph":"X","pid":0,"tid":3951767690,"ts":1289551550180},{"cat":"function","dur":916189,"name":"bool  WindowManager::Init(void)","ph":"X","pid":0,"tid":3951767690,"ts":1289551550243},{"cat":"function","dur":0,"name":"bool  SceneManager::Init(void)","ph":"X","pid":0,"tid":3951767690,"ts":1289552466706},{"cat":"function","dur":66,"name":"void  ResourceCatalog::createNewResource(class std::basic_string<char,struct std::char_traits<char>,class std::allocator<char> >,enum ResourceEntryType,bool)","ph":"X","pid":0,"tid":3951767690,"ts":1289552466774},{"cat":"function","dur":253,"name":"void  FileSystem::checkForFileUpdates(void *,unsigned int)","ph":"X","pid":0,"tid":3951767690,"ts":1289552466897},{"cat":"function","dur":41,"name":"void  ResourceCatalog::createNewResource(class std::basic_string<char,struct std::char_traits<char>,class std::allocator<char> >,enum ResourceEntryType,bool)","ph":"X","pid":0,"tid":3951767690,"ts":1289552708371},{"cat":"function","dur":33,"name":"void  SceneManager::UnloadCurrentScene(void)","ph":"X","pid":0,"tid":3951767690,"ts":1289552708490},{"cat":"function","dur":4065,"name":"bool  SceneManager::LoadSceneFromFile(class std::basic_string<char,struct std::char_traits<char>,class std::allocator<char> >,struct DataNode *)","ph":"X","pid":0,"tid":2227642938,"ts":1289552708343},{"cat":"function","dur":1456,"name":"void  SceneManager::CreateGameObjects(struct DataNode *)","ph":"X","pid":0,"tid":3951767690,"ts":1289552712860},{"cat":"function","dur":7401,"name":"bool  SceneManager::LoadNewScene(class std::basic_string<char,struct std::char_traits<char>,class std::allocator<char> >)","ph":"X","pid":0,"tid":3951767690,"ts":1289552707105},{"cat":"function","dur":104854,"name":"ErrorLogCheck","ph":"X","pid":0,"tid":3951767690,"ts":1289552714541}]}